{
  "item_id": "architectural_street_b80cab8d831d",
  "category": "architectural_street",
  "image_id": "191feb71272487c3",
  "caption": "In this picture I can see group of people standing, there is snow, there is a vehicle, there are buildings, there is fence, there are trees, and in the background there is the sky.",
  "caption_word_count": 34,
  "metadata": {
    "dataset": "open_images",
    "image_id": "191feb71272487c3"
  },
  "source": "localized_narratives_open_images",
  "retrieved_at": "2026-02-26T20:24:54.723415+00:00"
}