{
  "item_id": "architectural_street_a9c5c5ed535c",
  "category": "architectural_street",
  "image_id": "ee85b2d147e30643",
  "caption": "In the foreground of the picture there are plants, flowers, map, board and a person in white t-shirt. In the center of the picture there are trees, buildings, plants, grass and other objects. At the top it is sky.",
  "caption_word_count": 39,
  "metadata": {
    "dataset": "open_images",
    "image_id": "ee85b2d147e30643"
  },
  "source": "localized_narratives_open_images",
  "retrieved_at": "2026-02-26T20:24:44.429346+00:00"
}