{
  "item_id": "daily_indoors_6c396186d345",
  "category": "daily_indoors",
  "image_id": "bcfe95765255a2a0",
  "caption": "In the center of the image, we can see a mannequin and there are stands and some decors items and we can see a book. In the background, there are window, a door, a cctv camera and we can see some lights and there is a wall and a chair and we can see a rope.",
  "caption_word_count": 56,
  "metadata": {
    "dataset": "open_images",
    "image_id": "bcfe95765255a2a0"
  },
  "source": "localized_narratives_open_images",
  "retrieved_at": "2026-02-26T20:24:34.475209+00:00"
}