{
  "item_id": "architectural_street_c31f49b1afad",
  "category": "architectural_street",
  "image_id": "0fc7409b8c8a49cc",
  "caption": "In this picture there is a woman who is wearing grey t-shirt and trouser, beside him there is a girl who is holding green color object. In the bottom right corner i can see many chocolates which are kept in this basket. In the back there is a boy who is standing near to the door. At the top of the building there is a roof.",
  "caption_word_count": 66,
  "metadata": {
    "dataset": "open_images",
    "image_id": "0fc7409b8c8a49cc"
  },
  "source": "localized_narratives_open_images",
  "retrieved_at": "2026-02-26T20:27:00.480538+00:00"
}