{
  "item_id": "daily_indoors_3e2ced852ecd",
  "category": "daily_indoors",
  "image_id": "23cecfaa079aa7a8",
  "caption": "In this image I can see a person wearing black dress and a person wearing white dress are sitting on chair on the either sides of the table. On the table I can see few plates, few spoons, few tissue papers, few glasses and two flowers which are red in color. In the background I can see the white colored wall.",
  "caption_word_count": 61,
  "metadata": {
    "dataset": "open_images",
    "image_id": "23cecfaa079aa7a8"
  },
  "source": "localized_narratives_open_images",
  "retrieved_at": "2026-02-26T20:27:03.218080+00:00"
}