{
  "item_id": "architectural_street_5320160f33e6",
  "category": "architectural_street",
  "image_id": "005e5f3a11c71679",
  "caption": "In this image there is a person sitting on the couch, in front of the person there are empty couches and chairs, behind the person there are tables, stools, beside the person there is a glass wall with metal rods, at the top of the image there are lamps and logo, from the window we can see bushes, trees, cars, tents and buildings, at the top of the image there are clouds in the sky, in front of the stool there is a platform.",
  "caption_word_count": 84,
  "metadata": {
    "dataset": "open_images",
    "image_id": "005e5f3a11c71679"
  },
  "source": "localized_narratives_open_images",
  "retrieved_at": "2026-02-11T15:00:31.032034+00:00"
}