{
  "item_id": "architectural_street_1888db38acc3",
  "category": "architectural_street",
  "image_name": "1592219",
  "image_url": "https://cs.stanford.edu/people/rak248/VG_100K/1592219.jpg",
  "paragraph": "A street has the road closed. There are various object that are blocking the road, including an orange and white cone, an orange barricade and a large metal sign. The sign is standing on metal sign holder. There is a building behind the sign, it is large and brown. The road has a pot hole and it is filled with water.",
  "paragraph_word_count": 61,
  "source": "stanford_image_paragraph_captioning",
  "retrieved_at": "2026-02-26T12:41:33.132779+00:00"
}