{
  "item_id": "manufacturing_indoors_2cb377dc8da3",
  "category": "manufacturing_indoors",
  "image_name": "4151",
  "image_url": "https://cs.stanford.edu/people/rak248/VG_100K_2/4151.jpg",
  "paragraph": "There is a dark blue, clear night sky. In the forefront, there is granite-looking concrete. Beyond that, there is sidewalk that looks yellowish in the glow of evening lights. Farther back, there is a building with steel and scattered lights. There is heavy machinery visible through the building. The building itself appears to be a cross between a glass house and manufacturing facility. The left side of the building is shaped like a Lego-brick type of Christmas tree. The remaining building is more rectangular with a an staircase-type roof that looks like it is ascending towards the right side.",
  "paragraph_word_count": 99,
  "source": "stanford_image_paragraph_captioning",
  "retrieved_at": "2026-02-26T12:34:00.852836+00:00"
}