{
  "item_id": "architectural_street_4e19be33bbcc",
  "category": "architectural_street",
  "image_id": "a04d244d8066890a",
  "caption": "Here in this picture we can see number of people standing on the road over there and holding a banner in front of them and we can see number of flag post present in their hands and behind them we can see a building present and we can see trees present all over there.",
  "caption_word_count": 54,
  "metadata": {
    "dataset": "open_images",
    "image_id": "a04d244d8066890a"
  },
  "source": "localized_narratives_open_images",
  "retrieved_at": "2026-02-26T20:24:17.763227+00:00"
}