{
  "item_id": "daily_indoors_3c3ee0324d8d",
  "category": "daily_indoors",
  "image_key": "raw/daily_indoors/daily_indoors_3c3ee0324d8d/image.jpg",
  "objects": [],
  "raw_text": "Category: daily_indoors\n\nIn this image there is a man, he is wearing black color shirt and red color tie, in front of him there is a table, in the background it is blue.\n\nSource: Localized Narratives (Open Images)",
  "chunks_processed": 1,
  "distilled_at": "2026-02-26T20:37:55.323169+00:00",
  "stats": {
    "total_objects": 0,
    "spatially_referenced": 0,
    "not_spatially_referenced": 0
  }
}