{
  "item_id": "daily_indoors_fddf0fe35e5a",
  "category": "daily_indoors",
  "image_id": "946276cbdeeae8f8",
  "caption": "This is a black and white picture. On the background we can see a board. Here we can see persons sitting on chairs in front of a table and discussing. On the table we can see papers, book, water bottles and also mobile.",
  "caption_word_count": 43,
  "metadata": {
    "dataset": "open_images",
    "image_id": "946276cbdeeae8f8"
  },
  "source": "localized_narratives_open_images",
  "retrieved_at": "2026-02-26T20:26:43.845462+00:00"
}