{
  "item_id": "daily_indoors_3c09016d5bab",
  "category": "daily_indoors",
  "image_key": "raw/daily_indoors/daily_indoors_3c09016d5bab/image.jpg",
  "objects": [],
  "raw_text": "Category: daily_indoors\n\nIn the picture I can see some food item is kept on the white color plate, here I can see a bottle with a drink and a label on it, I can see tins and a few more objects are placed on the marble surface. In the background, I can see the wall.\n\nSource: Localized Narratives (Open Images)",
  "chunks_processed": 1,
  "distilled_at": "2026-02-26T20:37:53.863461+00:00",
  "stats": {
    "total_objects": 0,
    "spatially_referenced": 0,
    "not_spatially_referenced": 0
  }
}