{
  "item_id": "daily_indoors_b12183f32f27",
  "category": "daily_indoors",
  "image_id": "c0a112ac2f178bbb",
  "caption": "This is a black and white image where it consists of a sofa and there is a lamp on the right side. There is a photo frame to that wall. In that photo frame there is a picture of two horses.",
  "caption_word_count": 41,
  "metadata": {
    "dataset": "open_images",
    "image_id": "c0a112ac2f178bbb"
  },
  "source": "localized_narratives_open_images",
  "retrieved_at": "2026-02-26T20:24:16.927925+00:00"
}