{
  "item_id": "daily_indoors_566220a3e37f",
  "category": "daily_indoors",
  "image_id": "003008c10f5d3a1a",
  "caption": "In this image, on the right side, we can see a brick wall, glass window, light. On the right side, we can also see an electric pipe. In the middle of the image, we can see a window, brick wall. On the left side, we can see a window, brick wall. At the top, we can see white color, at the bottom, we can see a hoarding with some text written on it and a white color board.",
  "caption_word_count": 78,
  "metadata": {
    "dataset": "open_images",
    "image_id": "003008c10f5d3a1a"
  },
  "source": "localized_narratives_open_images",
  "retrieved_at": "2026-02-11T15:00:30.520997+00:00"
}