{
  "item_id": "daily_indoors_644644774c61",
  "category": "daily_indoors",
  "image_name": "1890",
  "image_url": "https://cs.stanford.edu/people/rak248/VG_100K_2/1890.jpg",
  "paragraph": "This is an image of a stairway. The stairs are very worn and are made of stone. The stairs have some green moss growing on them. The wall beside the stairs and old gray and brown stone. The wall is cracked. There is a large vase by the people at the top of the stairs. The vase is brown and black. The people are wearing white shirts. The man has one leg up against the wall.",
  "paragraph_word_count": 76,
  "source": "stanford_image_paragraph_captioning",
  "retrieved_at": "2026-02-26T12:41:44.811634+00:00"
}